{
  "version": "0.0.6-alpha",
  "default_questions": [
    {
      "id": 1,
      "category": {"fi": "Ympäristö", "en": "Environment", "sv": "Miljö"},
      "question": {
        "fi": "Pitäisikö kaupungin vähentää hiilidioksidipäästöjä 50% vuoteen 2030 mennessä?",
        "en": "Should the city reduce carbon dioxide emissions by 50% by 2030?",
        "sv": "Bör staden minska koldioxidutsläppen med 50 % till 2030?"
      },
      "tags": ["ympäristö", "hiilidioksidi", "ilmasto"],
      "scale": {"min": -5, "max": 5}
    },
    {
      "id": 2,
      "category": {"fi": "Liikenne", "en": "Transportation", "sv": "Transport"},
      "question": {
        "fi": "Pitäisikö kaupunkipyörien määrää lisätä kesäkaudella?",
        "en": "Should the number of city bikes be increased during summer season?",
        "sv": "Bör antalet stads cyklar ökas under sommarsäsongen?"
      },
      "tags": ["liikenne", "kaupunkipyörät", "kesä"],
      "scale": {"min": -5, "max": 5}
    }
  ],
  "default_candidates": [
    {
      "name": "Matti Meikäläinen",
      "party": "Test Puolue",
      "answers": [
        {"question_id": 1, "answer": 4, "confidence": 0.8},
        {"question_id": 2, "answer": 3, "confidence": 0.6}
      ]
    },
    {
      "name": "Liisa Esimerkki",
      "party": "Toinen Puolue",
      "answers": [
        {"question_id": 1, "answer": 2, "confidence": 0.5},
        {"question_id": 2, "answer": 5, "confidence": 0.8}
      ]
    }
  ],
  "justifications": {
    "fi": {
      "q1_pos": "Ilmastonmuutos on kiireellisin uhka, ja 50 % vähennys on välttämätön tavoite.",
      "q1_neg": "Tavoite on liian kunnianhimoinen nykyisellä teknologialla.",
      "q2_pos": "Kaupunkipyörät parantavat kaupunkikuva ja terveyttä.",
      "q2_neg": "Kaupunkipyörät ovat tärkeä osa kestävää liikkumista."
    },
    "en": {
      "q1_pos": "Climate change is the most urgent threat, and a 50% reduction is essential.",
      "q1_neg": "The target is too ambitious with current technology.",
      "q2_pos": "City bikes improve urban aesthetics and public health.",
      "q2_neg": "City bikes are an important part of sustainable mobility."
    },
    "sv": {
      "q1_pos": "Klimatförändringen är det största hotet, och en 50 % minskning är nödvändig.",
      "q1_neg": "Målet är för ambitiöst med nuvarande teknik.",
      "q2_pos": "Stadscyklar förbättrar stadsbilden och folkhälsan.",
      "q2_neg": "Stadscyklar är en viktig del av hållbar mobilitet."
    }
  }
}
